{"whitebox": {"fail": ["3", "2", "1", "7", "5", "4"], "pass": ["8", "6"]}, "revision": "523171ef9fdef92d324141ef9e678ff2e5c0720a", "nondeterministic": true, "output": {"whitebox": {"8": ["b'Please enter 4 numbers separated by spaces > 0 is the smallest\\n'", "b'Please enter 4 numbers separated by spaces > 0 is the smallest\\n'", "b'Please enter 4 numbers separated by spaces > 0 is the smallest\\n'", "b'Please enter 4 numbers separated by spaces > 0 is the smallest\\n'", "b'Please enter 4 numbers separated by spaces > 0 is the smallest\\n'", "b'Please enter 4 numbers separated by spaces > 0 is the smallest\\n'", "b'Please enter 4 numbers separated by spaces > 0 is the smallest\\n'", "b'Please enter 4 numbers separated by spaces > 0 is the smallest\\n'", "b'Please enter 4 numbers separated by spaces > 0 is the smallest\\n'", "b'Please enter 4 numbers separated by spaces > 0 is the smallest\\n'", "b'Please enter 4 numbers separated by spaces > 0 is the smallest\\n'"], "2": ["b'Please enter 4 numbers separated by spaces > '", "b'Please enter 4 numbers separated by spaces > '", "b'Please enter 4 numbers separated by spaces > '", "b'Please enter 4 numbers separated by spaces > '", "b'Please enter 4 numbers separated by spaces > '", "b'Please enter 4 numbers separated by spaces > '", "b'Please enter 4 numbers separated by spaces > '", "b'Please enter 4 numbers separated by spaces > '", "b'Please enter 4 numbers separated by spaces > '", "b'Please enter 4 numbers separated by spaces > '", "b'Please enter 4 numbers separated by spaces > '"], "7": ["b'Please enter 4 numbers separated by spaces > '", "b'Please enter 4 numbers separated by spaces > '", "b'Please enter 4 numbers separated by spaces > '", "b'Please enter 4 numbers separated by spaces > '", "b'Please enter 4 numbers separated by spaces > '", "b'Please enter 4 numbers separated by spaces > '", "b'Please enter 4 numbers separated by spaces > '", "b'Please enter 4 numbers separated by spaces > '", "b'Please enter 4 numbers separated by spaces > '", "b'Please enter 4 numbers separated by spaces > '", "b'Please enter 4 numbers separated by spaces > '"], "4": ["b'Please enter 4 numbers separated by spaces > '", "b'Please enter 4 numbers separated by spaces > '", "b'Please enter 4 numbers separated by spaces > '", "b'Please enter 4 numbers separated by spaces > '", "b'Please enter 4 numbers separated by spaces > '", "b'Please enter 4 numbers separated by spaces > '", "b'Please enter 4 numbers separated by spaces > '", "b'Please enter 4 numbers separated by spaces > '", "b'Please enter 4 numbers separated by spaces > '", "b'Please enter 4 numbers separated by spaces > '", "b'Please enter 4 numbers separated by spaces > '"], "5": ["b'Please enter 4 numbers separated by spaces > '", "b'Please enter 4 numbers separated by spaces > '", "b'Please enter 4 numbers separated by spaces > '", "b'Please enter 4 numbers separated by spaces > '", "b'Please enter 4 numbers separated by spaces > '", "b'Please enter 4 numbers separated by spaces > '", "b'Please enter 4 numbers separated by spaces > '", "b'Please enter 4 numbers separated by spaces > '", "b'Please enter 4 numbers separated by spaces > '", "b'Please enter 4 numbers separated by spaces > '", "b'Please enter 4 numbers separated by spaces > '"], "1": ["b'Please enter 4 numbers separated by spaces > '", "b'Please enter 4 numbers separated by spaces > '", "b'Please enter 4 numbers separated by spaces > '", "b'Please enter 4 numbers separated by spaces > '", "b'Please enter 4 numbers separated by spaces > '", "b'Please enter 4 numbers separated by spaces > '", "b'Please enter 4 numbers separated by spaces > '", "b'Please enter 4 numbers separated by spaces > '", "b'Please enter 4 numbers separated by spaces > '", "b'Please enter 4 numbers separated by spaces > '", "b'Please enter 4 numbers separated by spaces > '"], "6": ["b'Please enter 4 numbers separated by spaces > 0 is the smallest\\n'", "b'Please enter 4 numbers separated by spaces > 0 is the smallest\\n'", "b'Please enter 4 numbers separated by spaces > 0 is the smallest\\n'", "b'Please enter 4 numbers separated by spaces > 0 is the smallest\\n'", "b'Please enter 4 numbers separated by spaces > 0 is the smallest\\n'", "b'Please enter 4 numbers separated by spaces > 0 is the smallest\\n'", "b'Please enter 4 numbers separated by spaces > 0 is the smallest\\n'", "b'Please enter 4 numbers separated by spaces > 0 is the smallest\\n'", "b'Please enter 4 numbers separated by spaces > 0 is the smallest\\n'", "b'Please enter 4 numbers separated by spaces > 0 is the smallest\\n'", "b'Please enter 4 numbers separated by spaces > 0 is the smallest\\n'"], "3": ["b'Please enter 4 numbers separated by spaces > '", "b'Please enter 4 numbers separated by spaces > '", "b'Please enter 4 numbers separated by spaces > '", "b'Please enter 4 numbers separated by spaces > '", "b'Please enter 4 numbers separated by spaces > '", "b'Please enter 4 numbers separated by spaces > '", "b'Please enter 4 numbers separated by spaces > '", "b'Please enter 4 numbers separated by spaces > '", "b'Please enter 4 numbers separated by spaces > '", "b'Please enter 4 numbers separated by spaces > '", "b'Please enter 4 numbers separated by spaces > '"]}, "blackbox": {"8": ["b'Please enter 4 numbers separated by spaces > -1 is the smallest\\n'", "b'Please enter 4 numbers separated by spaces > -1 is the smallest\\n'", "b'Please enter 4 numbers separated by spaces > -1 is the smallest\\n'", "b'Please enter 4 numbers separated by spaces > -1 is the smallest\\n'", "b'Please enter 4 numbers separated by spaces > -1 is the smallest\\n'", "b'Please enter 4 numbers separated by spaces > -1 is the smallest\\n'", "b'Please enter 4 numbers separated by spaces > -1 is the smallest\\n'", "b'Please enter 4 numbers separated by spaces > -1 is the smallest\\n'", "b'Please enter 4 numbers separated by spaces > -1 is the smallest\\n'", "b'Please enter 4 numbers separated by spaces > -1 is the smallest\\n'", "b'Please enter 4 numbers separated by spaces > -1 is the smallest\\n'"], "2": ["b'Please enter 4 numbers separated by spaces > 4 is the smallest\\n'", "b'Please enter 4 numbers separated by spaces > 4 is the smallest\\n'", "b'Please enter 4 numbers separated by spaces > 4 is the smallest\\n'", "b'Please enter 4 numbers separated by spaces > 4 is the smallest\\n'", "b'Please enter 4 numbers separated by spaces > 4 is the smallest\\n'", "b'Please enter 4 numbers separated by spaces > 4 is the smallest\\n'", "b'Please enter 4 numbers separated by spaces > 4 is the smallest\\n'", "b'Please enter 4 numbers separated by spaces > 4 is the smallest\\n'", "b'Please enter 4 numbers separated by spaces > 4 is the smallest\\n'", "b'Please enter 4 numbers separated by spaces > 4 is the smallest\\n'", "b'Please enter 4 numbers separated by spaces > 4 is the smallest\\n'"], "7": ["b'Please enter 4 numbers separated by spaces > 0 is the smallest\\n'", "b'Please enter 4 numbers separated by spaces > 0 is the smallest\\n'", "b'Please enter 4 numbers separated by spaces > 0 is the smallest\\n'", "b'Please enter 4 numbers separated by spaces > 0 is the smallest\\n'", "b'Please enter 4 numbers separated by spaces > 0 is the smallest\\n'", "b'Please enter 4 numbers separated by spaces > 0 is the smallest\\n'", "b'Please enter 4 numbers separated by spaces > 0 is the smallest\\n'", "b'Please enter 4 numbers separated by spaces > 0 is the smallest\\n'", "b'Please enter 4 numbers separated by spaces > 0 is the smallest\\n'", "b'Please enter 4 numbers separated by spaces > 0 is the smallest\\n'", "b'Please enter 4 numbers separated by spaces > 0 is the smallest\\n'"], "4": ["b'Please enter 4 numbers separated by spaces > 3 is the smallest\\n'", "b'Please enter 4 numbers separated by spaces > 3 is the smallest\\n'", "b'Please enter 4 numbers separated by spaces > 3 is the smallest\\n'", "b'Please enter 4 numbers separated by spaces > 3 is the smallest\\n'", "b'Please enter 4 numbers separated by spaces > 3 is the smallest\\n'", "b'Please enter 4 numbers separated by spaces > 3 is the smallest\\n'", "b'Please enter 4 numbers separated by spaces > 3 is the smallest\\n'", "b'Please enter 4 numbers separated by spaces > 3 is the smallest\\n'", "b'Please enter 4 numbers separated by spaces > 3 is the smallest\\n'", "b'Please enter 4 numbers separated by spaces > 3 is the smallest\\n'", "b'Please enter 4 numbers separated by spaces > 3 is the smallest\\n'"], "5": ["b'Please enter 4 numbers separated by spaces > '", "b'Please enter 4 numbers separated by spaces > '", "b'Please enter 4 numbers separated by spaces > '", "b'Please enter 4 numbers separated by spaces > '", "b'Please enter 4 numbers separated by spaces > '", "b'Please enter 4 numbers separated by spaces > '", "b'Please enter 4 numbers separated by spaces > '", "b'Please enter 4 numbers separated by spaces > '", "b'Please enter 4 numbers separated by spaces > '", "b'Please enter 4 numbers separated by spaces > '", "b'Please enter 4 numbers separated by spaces > '"], "1": ["b'Please enter 4 numbers separated by spaces > 1 is the smallest\\n'", "b'Please enter 4 numbers separated by spaces > 1 is the smallest\\n'", "b'Please enter 4 numbers separated by spaces > 1 is the smallest\\n'", "b'Please enter 4 numbers separated by spaces > 1 is the smallest\\n'", "b'Please enter 4 numbers separated by spaces > 1 is the smallest\\n'", "b'Please enter 4 numbers separated by spaces > 1 is the smallest\\n'", "b'Please enter 4 numbers separated by spaces > 1 is the smallest\\n'", "b'Please enter 4 numbers separated by spaces > 1 is the smallest\\n'", "b'Please enter 4 numbers separated by spaces > 1 is the smallest\\n'", "b'Please enter 4 numbers separated by spaces > 1 is the smallest\\n'", "b'Please enter 4 numbers separated by spaces > 1 is the smallest\\n'"], "6": ["b'Please enter 4 numbers separated by spaces > '", "b'Please enter 4 numbers separated by spaces > '", "b'Please enter 4 numbers separated by spaces > '", "b'Please enter 4 numbers separated by spaces > '", "b'Please enter 4 numbers separated by spaces > '", "b'Please enter 4 numbers separated by spaces > '", "b'Please enter 4 numbers separated by spaces > '", "b'Please enter 4 numbers separated by spaces > '", "b'Please enter 4 numbers separated by spaces > '", "b'Please enter 4 numbers separated by spaces > '", "b'Please enter 4 numbers separated by spaces > '"], "3": ["b'Please enter 4 numbers separated by spaces > 3 is the smallest\\n'", "b'Please enter 4 numbers separated by spaces > 3 is the smallest\\n'", "b'Please enter 4 numbers separated by spaces > 3 is the smallest\\n'", "b'Please enter 4 numbers separated by spaces > 3 is the smallest\\n'", "b'Please enter 4 numbers separated by spaces > 3 is the smallest\\n'", "b'Please enter 4 numbers separated by spaces > 3 is the smallest\\n'", "b'Please enter 4 numbers separated by spaces > 3 is the smallest\\n'", "b'Please enter 4 numbers separated by spaces > 3 is the smallest\\n'", "b'Please enter 4 numbers separated by spaces > 3 is the smallest\\n'", "b'Please enter 4 numbers separated by spaces > 3 is the smallest\\n'", "b'Please enter 4 numbers separated by spaces > 3 is the smallest\\n'"]}}, "blackbox": {"fail": ["3", "2", "7", "6", "5", "4"], "pass": ["8", "1"]}}